[
    {
      "type": "text",
      "value": "Sein Markenzeichen ist das große Wandgemälde von Manuel Sierra, das die gesamte Fassade bedeckt und verschiedene ikonografische Motive der Vacceer zeigt. Es wurde am 21. September 2001 vom Rektor feierlich eingeweiht und hat sich seitdem als entscheidende Unterstützung für die Entwicklung des Projekts Pintia erwiesen, dessen Ziel es ist, das außergewöhnliche archäologische Erbe der archäologischen Zone Pintia zu schützen, zu erforschen und zu verbreiten. Wenn Sie das CEVFW kontaktieren möchten, können Sie dies über die Kontaktseite tun."
    },
    {
      "type": "image",
      "value": "https://pintiavaccea.es/imagenes_seccion/img201905031259.jpg"
    },
    {
      "type": "text",
      "value": "Das Zentrum trägt den Namen eines Professors der Universität Valladolid, der 1967 frühzeitig verstarb und mit seinem Werk *Die Vacceer-Region. Keltiberismus und Romanisierung im mittleren Duero-Becken* die Grundlagen für die Erforschung des Vacceer-Volkes legte. 2009 jährte sich die Veröffentlichung dieses Werkes zum fünfzigsten Mal. Zu diesem Anlass ehrte das CEVFW ihn mit einer bewegenden Hommage und errichtete ihm zu Ehren einen Gedenkstein auf dem Vacceer-Friedhof Las Ruedas."
    },
    {
      "type": "image",
      "value": "https://pintiavaccea.es/imagenes_seccion/img201903131240.jpg"
    }
  ]
  